revolutionhtl/DMSeries.py
revolutionhtl/NanNeighborJoining.py
revolutionhtl/__init__.py
revolutionhtl/__main__.py
revolutionhtl/blast.py
revolutionhtl/common_tools.py
revolutionhtl/constants.py
revolutionhtl/diamond.py
revolutionhtl/error.py
revolutionhtl/hello.py
revolutionhtl/hug_free.py
revolutionhtl/in_out.py
revolutionhtl/install_r_dependencies.py
revolutionhtl/lca_rmq.py
revolutionhtl/nhx_tools.py
revolutionhtl/nxTree.py
revolutionhtl/orthology.py
revolutionhtl/parse_prt.py
revolutionhtl/plot_functions.py
revolutionhtl/plot_reconciliation.py
revolutionhtl/plot_summary.py
revolutionhtl/prune.py
revolutionhtl/r_plot_summary.py
revolutionhtl/reconciliation.py
revolutionhtl/reduce_giant.py
revolutionhtl/supertree.py
revolutionhtl/tree_correction.py
revolutionhtl/tree_refinement.py
revolutionhtl/triplets.py
revolutionhtl-1.4.5.dist-info/licenses/LICENSE
revolutionhtl-1.4.5.dist-info/METADATA
revolutionhtl-1.4.5.dist-info/WHEEL
revolutionhtl-1.4.5.dist-info/top_level.txt
revolutionhtl-1.4.5.dist-info/RECORD
