Metadata-Version: 2.4
Name: revolutionhtl
Version: 1.4.5
Summary: REvolutionH-tl: Reconstruction of Evolutionary Histories tool
Project-URL: Homepage, https://gitlab.com/jarr.tecn/revolutionh-tl
Project-URL: Bug Tracker, https://gitlab.com/jarr.tecn/revolutionh-tl/issues
Keywords: Evolution reconstruction,Gene/species tree inference,Tree reconciliation,Orthology,Paralogy,Aligment hits,Best match graphs
Classifier: Programming Language :: Python :: 3
Classifier: License :: OSI Approved :: MIT License
Classifier: Operating System :: OS Independent
Requires-Python: >=3.7
License-File: LICENSE
Requires-Dist: networkx>=2.8
Requires-Dist: pandas>=1.4.2
Requires-Dist: numpy>=1.22.3
Requires-Dist: tqdm>=4.63.0
Requires-Dist: bmgedit
Requires-Dist: biopython
Requires-Dist: upsetplot
Requires-Dist: PyQt6
Requires-Dist: seaborn
Requires-Dist: scikit-learn
Requires-Dist: tqdm_joblib
Requires-Dist: PyPDF2
Dynamic: license-file
